mdtool/__init__.py
"mdtool/cli/,hb_distribution.py"
"mdtool/cli/,hb_distribution_down.py"
mdtool/cli/adsorbate.py
mdtool/cli/build_bulk.py
mdtool/cli/build_interface.py
mdtool/cli/build_surface.py
mdtool/cli/cmdline.py
mdtool/cli/convert.py
mdtool/cli/cp2k_input.py
mdtool/cli/cube.py
mdtool/cli/cut_surface.py
mdtool/cli/data.py
mdtool/cli/density.py
mdtool/cli/density2.py
mdtool/cli/extract.py
mdtool/cli/hartree_potential.py
mdtool/cli/hartree_potential_ave.py
mdtool/cli/hb.py
mdtool/cli/log.py
mdtool/cli/matplot.py
mdtool/cli/packmol_input.py
mdtool/cli/pdos.py
mdtool/cli/plot.py
mdtool/cli/supercell.py
mdtool/cli/wrap.py
mdtool/config/__init__.py
mdtool/config/settings.yml
mdtool/mdtool.py
mdtool/util/__init__.py
mdtool/util/arg_type.py
mdtool/util/cp2k_input_parsing.py
mdtool/util/encapsulated_ase.py
mdtool/util/encapsulated_mda.py
mdtool/util/fig_operation.py
mdtool/util/numpy_geo.py
mdtool/util/os_operation.py
mdtool/util/structure_parsing.py
mdtool-0.1.10.dist-info/entry_points.txt
mdtool-0.1.10.dist-info/LICENSE
mdtool-0.1.10.dist-info/METADATA
mdtool-0.1.10.dist-info/WHEEL
mdtool-0.1.10.dist-info/RECORD
